{
  "id": 2107,
  "created_username": " astang@caltech.edu, 2",
  "created_ago": "23\u00a0hours, 55\u00a0minutes",
  "task": {
    "id": 10793,
    "data": {
      "image": "/data/local-files/?d=programming/Robotics/label-studio/fsri2022-dataset/training_data/A/A2_910.jpg"
    },
    "meta": {},
    "created_at": "2022-08-13T07:17:46.281374Z",
    "updated_at": "2022-08-13T08:59:59.969496Z",
    "is_labeled": true,
    "overlap": 1,
    "inner_id": 1635,
    "total_annotations": 1,
    "cancelled_annotations": 0,
    "total_predictions": 0,
    "project": 1,
    "updated_by": 2,
    "file_upload": null
  },
  "completed_by": {
    "id": 2,
    "first_name": "",
    "last_name": "",
    "email": "astang@caltech.edu"
  },
  "result": [
    {
      "original_width": 320,
      "original_height": 180,
      "image_rotation": 0,
      "value": {
        "x": 33.125,
        "y": 10,
        "width": 45.3125,
        "height": 68.33333333333333,
        "rotation": 0,
        "rectanglelabels": [
          "A Block"
        ]
      },
      "id": "z50S2pYn72",
      "from_name": "label",
      "to_name": "image",
      "type": "rectanglelabels",
      "origin": "manual"
    }
  ],
  "was_cancelled": false,
  "ground_truth": false,
  "created_at": "2022-08-13T08:59:59.938863Z",
  "updated_at": "2022-08-13T08:59:59.938883Z",
  "lead_time": 2.125,
  "parent_prediction": null,
  "parent_annotation": null
}