{
  "id": 619,
  "created_username": "Luke Alvidrez alvidrezluke@gmail.com, 1",
  "created_ago": "49\u00a0minutes",
  "task": {
    "id": 9329,
    "data": {
      "image": "/data/local-files/?d=programming/Robotics/label-studio/fsri2022-dataset/training_data/A/A1_277.jpg"
    },
    "meta": {},
    "created_at": "2022-08-13T07:17:36.166199Z",
    "updated_at": "2022-08-13T07:36:49.123829Z",
    "is_labeled": true,
    "overlap": 1,
    "inner_id": 171,
    "total_annotations": 1,
    "cancelled_annotations": 0,
    "total_predictions": 0,
    "project": 1,
    "updated_by": 1,
    "file_upload": null
  },
  "completed_by": {
    "id": 1,
    "first_name": "Luke",
    "last_name": "Alvidrez",
    "email": "alvidrezluke@gmail.com"
  },
  "result": [
    {
      "original_width": 320,
      "original_height": 180,
      "image_rotation": 0,
      "value": {
        "x": 30.9375,
        "y": 12.777777777777779,
        "width": 54.6875,
        "height": 76.11111111111111,
        "rotation": 0,
        "rectanglelabels": [
          "A Block"
        ]
      },
      "id": "yWRbXbyUSB",
      "from_name": "label",
      "to_name": "image",
      "type": "rectanglelabels",
      "origin": "manual"
    }
  ],
  "was_cancelled": false,
  "ground_truth": false,
  "created_at": "2022-08-13T07:36:49.090589Z",
  "updated_at": "2022-08-13T07:36:49.090623Z",
  "lead_time": 1.889,
  "parent_prediction": null,
  "parent_annotation": null
}