{
  "id": 9993,
  "created_username": " astang@caltech.edu, 2",
  "created_ago": "6\u00a0hours, 16\u00a0minutes",
  "task": {
    "id": 18139,
    "data": {
      "image": "/data/local-files/?d=programming/Robotics/label-studio/fsri2022-dataset/training_data/BlocksWithoutVowels/PXL_20220801_184135353.jpg"
    },
    "meta": {},
    "created_at": "2022-08-13T07:18:52.039255Z",
    "updated_at": "2022-08-14T02:40:52.888402Z",
    "is_labeled": true,
    "overlap": 1,
    "inner_id": 8981,
    "total_annotations": 1,
    "cancelled_annotations": 0,
    "total_predictions": 0,
    "project": 1,
    "updated_by": 2,
    "file_upload": null
  },
  "completed_by": {
    "id": 2,
    "first_name": "",
    "last_name": "",
    "email": "astang@caltech.edu"
  },
  "result": [
    {
      "original_width": 3072,
      "original_height": 4080,
      "image_rotation": 0,
      "value": {
        "x": 40.848214285714285,
        "y": 14.285714285714286,
        "width": 45.089285714285715,
        "height": 37.3109243697479,
        "rotation": 0,
        "rectanglelabels": [
          "Consonant Block"
        ]
      },
      "id": "G-GeLTFLwT",
      "from_name": "label",
      "to_name": "image",
      "type": "rectanglelabels",
      "origin": "manual"
    }
  ],
  "was_cancelled": false,
  "ground_truth": false,
  "created_at": "2022-08-14T02:40:52.845038Z",
  "updated_at": "2022-08-14T02:40:52.845057Z",
  "lead_time": 2.53,
  "parent_prediction": null,
  "parent_annotation": null
}